lambdser/__init__.py
lambdser/lambdser.py
lambdser-0.1.2.dist-info/LICENSE.md
lambdser-0.1.2.dist-info/METADATA
lambdser-0.1.2.dist-info/WHEEL
lambdser-0.1.2.dist-info/top_level.txt
lambdser-0.1.2.dist-info/RECORD
