Metadata-Version: 2.1
Name: lambdser
Version: 0.1.2
Summary: fast lambda expression serializer
Home-page: https://github.com/cloasdata/lambdser
Author: Simon Bauer
Author-email: code@seimenadventure.de
License: MIT
Keywords: dill,lambda,serializer,pickle
Classifier: Programming Language :: Python :: 3
Classifier: License :: OSI Approved :: MIT License
Classifier: Operating System :: OS Independent
License-File: LICENSE.md
Requires-Dist: importlib-metadata ; python_version >= "3.10"
Provides-Extra: test
Requires-Dist: pytest >=7.0.0 ; extra == 'test'
Requires-Dist: dill >=0.3.4 ; extra == 'test'
